gopro_video_sync/__init__.py
gopro_video_sync/audio_offset.py
gopro_video_sync/cross_correlation.py
gopro_video_sync/gopro_data.py
gopro_video_sync/offset.py
gopro_video_sync/sensor_offset.py
gopro_video_sync-0.0.3.dist-info/LICENSE
gopro_video_sync-0.0.3.dist-info/METADATA
gopro_video_sync-0.0.3.dist-info/WHEEL
gopro_video_sync-0.0.3.dist-info/top_level.txt
gopro_video_sync-0.0.3.dist-info/RECORD
