Metadata-Version: 2.1
Name: gopro-video-sync
Version: 0.0.3
Summary: A tool to determine the offset between videos from two jointly mounted GoPros based on a combination of audio, accelerometer, and gyroscope data.
Home-page: https://github.com/evoth/gopro-video-sync
Author: Ethan Voth
Author-email: ethanvoth7@gmail.com
Classifier: Programming Language :: Python :: 3
Classifier: License :: OSI Approved :: MIT License
Classifier: Operating System :: OS Independent
License-File: LICENSE
Requires-Dist: moviepy
Requires-Dist: numpy
Requires-Dist: scipy
